BivTrunc/BivTruncF.cpython-37m-darwin.so
BivTrunc/BivTruncPy.py
BivTrunc/__init__.py
BivTrunc-0.0.38.dist-info/LICENSE
BivTrunc-0.0.38.dist-info/METADATA
BivTrunc-0.0.38.dist-info/WHEEL
BivTrunc-0.0.38.dist-info/top_level.txt
BivTrunc-0.0.38.dist-info/RECORD
